ocr_stringdist-1.0.1.dist-info/METADATA
ocr_stringdist-1.0.1.dist-info/WHEEL
ocr_stringdist-1.0.1.dist-info/licenses/LICENSE
ocr_stringdist/__init__.py
ocr_stringdist/_rust_stringdist.cp312-win32.pyd
ocr_stringdist/default_ocr_distances.py
ocr_stringdist/edit_operation.py
ocr_stringdist/learner.py
ocr_stringdist/levenshtein.py
ocr_stringdist/matching.py
ocr_stringdist/protocols.py
ocr_stringdist/py.typed
ocr_stringdist-1.0.1.dist-info/RECORD
