Metadata-Version: 2.4
Name: ocr-stringdist
Version: 1.0.1
Classifier: Programming Language :: Rust
Classifier: Programming Language :: Python :: Implementation :: CPython
Classifier: License :: OSI Approved :: MIT License
Classifier: Operating System :: OS Independent
License-File: LICENSE
Requires-Python: >=3.9
Project-URL: repository, https://github.com/NiklasvonM/ocr-stringdist
Project-URL: documentation, https://niklasvonm.github.io/ocr-stringdist/
